ssb_coefficient_maker/__init__.py
ssb_coefficient_maker/__main__.py
ssb_coefficient_maker/coeff_maker.py
ssb_coefficient_maker/py.typed
ssb_coefficient_maker-1.0.2.dist-info/LICENSE
ssb_coefficient_maker-1.0.2.dist-info/METADATA
ssb_coefficient_maker-1.0.2.dist-info/WHEEL
ssb_coefficient_maker-1.0.2.dist-info/entry_points.txt
ssb_coefficient_maker-1.0.2.dist-info/RECORD
