Metadata-Version: 2.3
Name: ssb-coefficient-maker
Version: 1.0.2
Summary: SSB Coefficient Maker
License: MIT
Author: Benedikt Goodman
Author-email: goodmanbenedikt@gmail.com
Requires-Python: >=3.10,<4.0
Classifier: Development Status :: 4 - Beta
Classifier: License :: OSI Approved :: MIT License
Classifier: Programming Language :: Python :: 3
Classifier: Programming Language :: Python :: 3.10
Classifier: Programming Language :: Python :: 3.11
Classifier: Programming Language :: Python :: 3.12
Classifier: Programming Language :: Python :: 3.13
Requires-Dist: click (>=8.0.1)
Requires-Dist: mpmath (>=1.3.0,<2.0.0)
Requires-Dist: numpy (>=2.2.3,<3.0.0)
Requires-Dist: pandas (>=2.2.3,<3.0.0)
Requires-Dist: pydantic (>=2.10.6,<3.0.0)
Requires-Dist: sympy (>=1.13.3,<2.0.0)
Project-URL: Changelog, https://github.com/statisticsnorway/ssb-coefficient-maker/releases
Project-URL: Documentation, https://statisticsnorway.github.io/ssb-coefficient-maker
Project-URL: Homepage, https://github.com/statisticsnorway/ssb-coefficient-maker
Project-URL: Repository, https://github.com/statisticsnorway/ssb-coefficient-maker
